[
    {
        "name": "Disco Dancers",
        "expansion": "That '70s Expansion",
        "teaser": "Duplicate the effects caused by standard actions on minions, thus increasing the number of affected minions.",
        "mechanics": "Duplicate the effects caused by standard actions on minions, thus increasing the number of affected minions.",
        "playstyle": "High",
        "description": "",
        "cardsTeaser": "",
        "actionTeaser": "",
        "actionList": "",
        "actions": "",
        "characters": "",
        "bases": "",
        "clarifications": "",
        "suggestionTeaser": "",
        "synergy": "",
        "tips": "",
        "effects": "",
        "image": ""
    },
    {
        "name": "Kung Fu Fighters",
        "expansion": "That '70s Expansion",
        "teaser": "Generate +1 power counters, drain them from any minions, even other players', and destroy weaker minions.",
        "mechanics": "Generate +1 power counters, drain them from any minions, even other players', and destroy weaker minions.",
        "playstyle": "Medium-High",
        "description": "",
        "cardsTeaser": "",
        "actionTeaser": "",
        "actionList": "",
        "actions": "",
        "characters": "",
        "bases": "",
        "clarifications": "",
        "suggestionTeaser": "",
        "synergy": "",
        "tips": "",
        "effects": "",
        "image": ""
    },
    {
        "name": "Truckers",
        "expansion": "That '70s Expansion",
        "teaser": "Transfer play-on-base actions around in order to move your minions, and mess with other players' play-on-base actions, either by transferring them elsewhere or taking control of them.",
        "mechanics": "Transfer play-on-base actions around in order to move your minions, and mess with other players' play-on-base actions, either by transferring them elsewhere or taking control of them.",
        "playstyle": "Low-Medium",
        "description": "",
        "cardsTeaser": "",
        "actionTeaser": "",
        "actionList": "",
        "actions": "",
        "characters": "",
        "bases": "",
        "clarifications": "",
        "suggestionTeaser": "",
        "synergy": "",
        "tips": "",
        "effects": "",
        "image": ""
    },
    {
        "name": "Vigilantes",
        "expansion": "That '70s Expansion",
        "teaser": "Play with a reduced number of minions in your deck, but with a team of seven power-4 minions with powerful and oppressive abilities, including hard removal, power boost and retaliation.",
        "mechanics": "Play with a reduced number of minions in your deck, but with a team of seven power-4 minions with powerful and oppressive abilities, including hard removal, power boost and retaliation.",
        "playstyle": "High",
        "description": "",
        "cardsTeaser": "",
        "actionTeaser": "",
        "actionList": "",
        "actions": "",
        "characters": "",
        "bases": "",
        "clarifications": "",
        "suggestionTeaser": "",
        "synergy": "",
        "tips": "",
        "effects": "",
        "image": ""
    }
]
